magneto.cp310-win_amd64.pyd
magneto_search-2.0.0.dist-info/licenses/LICENSE
magneto_search-2.0.0.dist-info/METADATA
magneto_search-2.0.0.dist-info/WHEEL
magneto_search-2.0.0.dist-info/top_level.txt
magneto_search-2.0.0.dist-info/RECORD
